Workbook

Sheet Leia-me
A1: Concorrentes: plataforma de flashcards
A2: Levantamento de 06/10/2026, feito a partir dos sites e lojas de apps. Preços mudam: confira antes de usar num pitch.
A4: Abas
A5: Concorrentes: quem é, quanto custa, pontos fortes, a brecha para nós e a fonte.
A6: Funcionalidades: matriz Sim / Parcial / Não / ? e, embaixo, quantos concorrentes têm cada recurso (fórmulas).
A7: Premissas: câmbio usado para converter preços em dólar.
A9: Legenda
A10: Texto azul = valor digitado à mão (preço, câmbio). Preto = fórmula.
A11: Fundo amarelo = premissa que você deve conferir/atualizar.
A12: ? = não encontrei informação pública. Vale testar o app ou perguntar ao suporte.
A13: Coluna Confiança: Alta = site/loja oficial; Média = comparativo de terceiros ou avaliação sua anterior; Baixa = informação escassa.
A15: Para adicionar um concorrente
... A23: 4. Ninguém junta cards próprios + importação do Anki + FSRS + Consulta com grifos, num app Android offline. Esse é o espaço.

Sheet Concorrentes
A1: Concorrente | B1: Segmento | C1: Tipo | D1: Áreas | E1: Plataformas | F1: Modelo de cobrança | G1: Preço (valor) | H1: Moeda | I1: Meses cobertos | J1: R$/mês | K1: Detalhe do preço | L1: Pontos fortes | M1: Brecha para nós | N1: Fonte | O1: Confiança
A2: Anki (desktop, AnkiDroid, AnkiMobile) | B2: Generalista global | C2: Direto | D2: Qualquer | E2: Win/Mac/Linux, Android, iOS, AnkiWeb | F2: Grátis; iOS pago único | G2: 24.99 | H2: USD | J2: =IF(OR(G2="",I2=""),"-",G2*IF(H2="USD",Premissas!$B$3,1)/I2) -> - | K2: Desktop e AnkiDroid grátis; AnkiMobile US$24,99 pagamento único. | L2: FSRS (disponível desde a versão 23.10), oclusão de imagem nativa, add-ons, base enorme de decks compartilhados. Padrão de fato em med e concurso. | M2: Barreira de entrada (configuração, modelos, add-ons) e visual datado. Consulta e grifos só via add-on no desktop. | N2: https://apps.apple.com/us/app/ankimobile-flashcards/id373493387 ; https://www.mindomax.com/is-anki-free | O2: Alta
A3: Noji (ex-AnkiPro) | B3: Generalista global | C3: Direto | D3: Idiomas, geral | E3: iOS, Android, web | F3: Freemium + assinatura | G3: 29.99 | H3: USD | I3: 12 | J3: =IF(OR(G3="",I3=""),"-",G3*IF(H3="USD",Premissas!$B$3,1)/I3) -> 13.4955 | K3: US$4,99/mês; US$29,99/ano; US$74,99 vitalício (varia por país). | L3: O mais próximo da ideia 'Anki bonito e simples'. Importa .apkg/.colpkg, CSV e Quizlet. Biblioteca de 50 mil decks. | M3: Comparativos apontam SM-2 com presets, sem FSRS. Foco em idiomas, nada específico de med/concurso BR, sem modo de leitura. | N3: https://apps.apple.com/BR/app/id1573585542 ; https://help.noji.io/en/articles/9659298-can-i-import-other-decks-from-anki | O3: Média
A4: RemNote | B4: Generalista global | C4: Direto | D4: Universitário, med (EUA) | E4: Web, desktop, iOS, Android | F4: Freemium + assinatura | G4: 8 | H4: USD | I4: 1 | J4: =IF(OR(G4="",I4=""),"-",G4*IF(H4="USD",Premissas!$B$3,1)/I4) -> 43.2 | K4: Pro US$8/mês; Pro com IA US$18/mês. | L4: Notas + flashcards no mesmo lugar, FSRS, anotação de PDF com grifos, agenda de provas, IA. | M4: Curva de aprendizado alta (é um app de notas). O grifo fica no PDF ou na nota, não no verso de um card revisado. Sem conteúdo BR. | N4: https://toolradar.com/tools/remnote/pricing ; https://alpha.remnote.com/blog/remnote-vs-anki | O4: Média
A5: Quizlet | B5: Generalista global | C5: Direto | D5: Escolar, idiomas | E5: Web, iOS, Android | F5: Freemium + assinatura | G5: 35.99 | H5: USD | I5: 12 | J5: =IF(OR(G5="",I5=""),"-",G5*IF(H5="USD",Premissas!$B$3,1)/I5) -> 16.1955 | K5: Plus US$7,99/mês ou US$35,99/ano; Plus Unlimited US$44,99/ano. | L5: Marca conhecida, muitos sets em PT-BR feitos por usuários, IA. | M5: Sem FSRS e sem importar Anki. O plano grátis vem sendo cortado. Pouco usado para estudo de longo prazo. | N5: https://nibble-app.com/blog/quizlet-cost | O5: Média
A6: Brainscape | B6: Generalista global | C6: Direto | D6: Geral, med (EUA) | E6: Web, iOS, Android | F6: Freemium + assinatura | G6: 95.99 | H6: USD | I6: 12 | J6: =IF(OR(G6="",I6=""),"-",G6*IF(H6="USD",Premissas!$B$3,1)/I6) -> 43.1955 | K6: Pro US$19,99/mês; US$95,99/ano; vitalício US$199,99. | L6: Repetição por confiança (nota 1–5), decks prontos certificados. | M6: Caro, algoritmo próprio pouco transparente, sem importação do Anki, nada BR. | N6: https://softwarefinder.com/lms/brainscape/pricing | O6: Média
A7: Mochi | B7: Generalista global | C7: Direto | D7: Geral, programação | E7: Web, desktop, iOS, Android | F7: Freemium + assinatura | G7: 5 | H7: USD | I7: 1 | J7: =IF(OR(G7="",I7=""),"-",G7*IF(H7="USD",Premissas!$B$3,1)/I7) -> 27 | K7: Pro US$5/mês, cobrado anualmente. | L7: Minimalista, cards em Markdown, grátis e offline sem limite. | M7: Nicho pequeno e técnico, sem conteúdo nem marketing no Brasil. | N7: https://mochi.cards/pricing/ | O7: Média
A8: MemorizeCards | B8: Concursos BR | C8: Direto | D8: Policial, jurídica, fiscal, administrativa | E8: Só navegador (sem app nativo) | F8: Assinatura | G8: 449.9 | H8: BRL | I8: 12 | J8: =IF(OR(G8="",I8=""),"-",G8*IF(H8="USD",Premissas!$B$3,1)/I8) -> 37.491667 | K8: R$49,90/mês; R$249,90 semestral; R$449,90 anual. | L8: 3,4 milhões de cards prontos, anotação pessoal no card, caderno de erros, leitura em voz alta. | M8: Não tem app nativo nem modo offline. Algoritmo não divulgado. Cards fechados: não dá para trazer os do Anki. | N8: https://memorizecards.com.br/ | O8: Alta
A9: Decoreba | B9: Concursos BR | C9: Direto | D9: ENEM, concursos | E9: iOS, Android | F9: Freemium + assinatura | G9: 29.9 | H9: BRL | I9: 1 | J9: =IF(OR(G9="",I9=""),"-",G9*IF(H9="USD",Premissas!$B$3,1)/I9) -> 29.9 | K9: Premium a partir de R$29,90/mês; tem trimestral. | L9: App nativo, 5 mil cards grátis, questões, simulados, IA que explica, 'Raio-X dos temas'. | M9: Conteúdo pronto deles; não fala em cards próprios nem importação. Sem modo de leitura. | N9: http://decoreba-app.com/home/ | O9: Alta
A10: IAprova | B10: Concursos BR | C10: Direto | D10: Concursos, ENEM, vestibulares | E10: Web + PWA (sem loja) | F10: Trial + assinatura | G10: 29.9 | H10: BRL | I10: 1 | J10: =IF(OR(G10="",I10=""),"-",G10*IF(H10="USD",Premissas!$B$3,1)/I10) -> 29.9 | K10: R$29,90/mês (15 créditos de IA/dia); trial de 14 dias; anual com desconto. | L10: Plano de estudo com IA, questões no estilo de 15+ bancas, correção de redação, flashcards gerados por IA. ~1.400 alunos. | M10: O usuário não cria os próprios cards; sem app de loja; sem FSRS declarado. É a referência de preço para o nosso premium. | N10: https://iaprova.app/home | O10: Alta
A11: RevisaCards | B11: Concursos BR | C11: Direto | D11: Carreiras policiais e administrativas | E11: Entrega decks para o Anki | F11: Pacote único | G11: 297 | H11: BRL | J11: =IF(OR(G11="",I11=""),"-",G11*IF(H11="USD",Premissas!$B$3,1)/I11) -> - | K11: Pacotes R$247–297; combos R$397–497; cronograma R$297 (preços promocionais). | L11: Vende decks Anki prontos + cronograma, com prova social ('2.000 aprovados'). | M11: Depende do Anki, com toda a barreira dele. Mostra que existe gente pagando por 'deck + cronograma': nosso app pode ser onde esses decks rodam. | N11: https://revisacards.com/ | O11: Alta
A12: Cards de Concursos | B12: Concursos BR | C12: Direto | D12: Concursos | E12: Mobile, offline (segundo o site) | F12: Grátis (declarado) | G12: 0 | H12: BRL | I12: 1 | J12: =IF(OR(G12="",I12=""),"-",G12*IF(H12="USD",Premissas!$B$3,1)/I12) -> 0 | K12: Anuncia flashcards grátis; o site quase não tem informação. | L12: Grátis, offline. | M12: Informação pública escassa: testar o app. | N12: https://cardsdeconcursos.com.br/ | O12: Baixa
A13: Osler | B13: Medicina BR | C13: Direto | D13: Residência médica | E13: Web app | F13: Assinatura de curso | G13: 5124 | H13: BRL | I13: 28 | J13: =IF(OR(G13="",I13=""),"-",G13*IF(H13="USD",Premissas!$B$3,1)/I13) -> 183 | K13: R$5.124 por 28 meses (sua avaliação de 17/09/2026). Curso completo: flashcards + QBank. | L13: ~90 mil flashcards, Modo Consulta, FSRS próprio (só retenção e intervalo máx.), 'Meus cards', High Yield, incidência por banca. | M13: Caro e preso ao curso; não importa histórico nem pesos do Anki. Modo Consulta só para o conteúdo deles. | N13: Sua avaliação da plataforma em 17/09/2026 | O13: Média
A14: Medcof | B14: Medicina BR | C14: Direto | D14: Residência médica | E14: Web, app | F14: Assinatura de curso | H14: BRL | J14: =IF(OR(G14="",I14=""),"-",G14*IF(H14="USD",Premissas!$B$3,1)/I14) -> - | K14: Preço não encontrado; flashcards vêm dentro da plataforma do curso. | L14: Flashcards prontos + cards próprios integrados ao QBank e ao curso. | M14: Preso ao curso; sem importação do Anki conhecida. | N14: https://www.grupomedcof.com.br/blog/flashcards-medcof/ | O14: Média
A15: Estratégia MED (Flashcards + Mapas) | B15: Medicina BR | C15: Direto | D15: Residência médica | E15: Web, app | F15: Produto avulso | G15: 1067.4 | H15: BRL | J15: =IF(OR(G15="",I15=""),"-",G15*IF(H15="USD",Premissas!$B$3,1)/I15) -> - | K15: 12x R$88,95; período de acesso não informado. | L15: Marca forte, produto de flashcards vendido separado do curso. | M15: Cards só deles; sem cards próprios nem Anki conhecidos. | N15: https://med.estrategia.com/curso/flashcards-mapas-mentais/ | O15: Média
A16: Gran Cursos | B16: Concursos BR | C16: Indireto | D16: Concursos | E16: Web, app | F16: Assinatura ilimitada | H16: BRL | J16: =IF(OR(G16="",I16=""),"-",G16*IF(H16="USD",Premissas!$B$3,1)/I16) -> - | K16: Flashcards em PDF para imprimir, dentro da assinatura ilimitada. | L16: Enorme base de alunos. | M16: Flashcard em PDF, sem repetição espaçada: o aluno do Gran é público natural para o nosso app. | N16: https://blog.grancursosonline.com.br/flashcards/amp/ | O16: Média
A17: Qconcursos / TEC | B17: Concursos BR | C17: Indireto | D17: Concursos, OAB | E17: Web, app | F17: Assinatura | H17: BRL | J17: =IF(OR(G17="",I17=""),"-",G17*IF(H17="USD",Premissas!$B$3,1)/I17) -> - | K17: Plataformas de questões; flashcards não confirmados. | L17: Banco de questões com filtro por banca e órgão. | M17: Complementar: questões lá, revisão no nosso app. | N17: https://tecnoblog.net/responde/5-aplicativos-para-estudar-para-concurso-publico/ | O17: Baixa
A19: R$/mês = preço × câmbio (se USD) ÷ meses cobertos. '-' quando o pagamento é único ou o preço/período não foi encontrado.
A20: Mediana R$/mês (concorrentes com preço mensalizável) | J20: =MEDIAN(J2:J17) -> 29.9
A21: Mediana R$/mês só concorrentes BR | J21: {=MEDIAN(IF((H2:H17="BRL")*ISNUMBER(J2:J17),J2:J17))} -> 29.9

Sheet Funcionalidades
A1: Concorrente | B1: Modo Consulta (versos como texto) | C1: Grifo/nota no texto do card | D1: Grifo aparece na revisão | E1: FSRS | F1: Cria cards próprios | G1: Cards prontos em PT-BR | H1: Importa .apkg | I1: Offline | J1: App Android de loja | K1: Web | L1: IA (gerar/explicar) | M1: Plano/cronograma | N1: Uso grátis real
A2: Anki | B2: Não | C2: Não | D2: Não | E2: Sim | F2: Sim | G2: Parcial | H2: Sim | I2: Sim | J2: Sim | K2: Parcial | L2: Não | M2: Não | N2: Sim
A3: Noji | B3: Não | C3: ? | D3: ? | E3: Não | F3: Sim | G3: Parcial | H3: Sim | I3: ? | J3: Sim | K3: Sim | L3: Sim | M3: Não | N3: Sim
A4: RemNote | B4: Parcial | C4: Sim | D4: Não | E4: Sim | F4: Sim | G4: Não | H4: Sim | I4: Sim | J4: Sim | K4: Sim | L4: Sim | M4: Parcial | N4: Sim
A5: Quizlet | B5: Não | C5: Não | D5: Não | E5: Não | F5: Sim | G5: Sim | H5: Não | I5: Parcial | J5: Sim | K5: Sim | L5: Sim | M5: Parcial | N5: Parcial
A6: Brainscape | B6: Não | C6: Não | D6: Não | E6: Não | F6: Sim | G6: Parcial | H6: Não | I6: Parcial | J6: Sim | K6: Sim | L6: ? | M6: Não | N6: Parcial
A7: Mochi | B7: Não | C7: Não | D7: Não | E7: ? | F7: Sim | G7: Não | H7: Sim | I7: Sim | J7: Sim | K7: Sim | L7: ? | M7: Não | N7: Sim
A8: MemorizeCards | B8: ? | C8: Parcial | D8: ? | E8: ? | F8: Parcial | G8: Sim | H8: Não | I8: Não | J8: Não | K8: Sim | L8: Não | M8: ? | N8: ?
A9: Decoreba | B9: Não | C9: Não | D9: Não | E9: ? | F9: ? | G9: Sim | H9: Não | I9: ? | J9: Sim | K9: Não | L9: Sim | M9: Parcial | N9: Sim
A10: IAprova | B10: Não | C10: Não | D10: Não | E10: ? | F10: Não | G10: Sim | H10: Não | I10: Não | J10: Não | K10: Sim | L10: Sim | M10: Sim | N10: Parcial
A11: RevisaCards | B11: Não | C11: Não | D11: Não | E11: Sim | F11: Sim | G11: Sim | H11: Sim | I11: Sim | J11: Sim | K11: Parcial | L11: Não | M11: Sim | N11: Não
A12: Cards de Concursos | B12: ? | C12: ? | D12: ? | E12: ? | F12: ? | G12: Sim | H12: ? | I12: Sim | J12: ? | K12: ? | L12: ? | M12: ? | N12: Sim
... A16: Nós (MVP) | B16: Sim | C16: Sim | D16: Sim | E16: Sim | F16: Sim | G16: Parcial | H16: Sim | I16: Sim | J16: Sim | K16: Depois | L16: Não | M16: Depois | N16: Sim
A18: Concorrentes com Sim | B18: =COUNTIF(B2:B15,"Sim") -> 1 | C18: =COUNTIF(C2:C15,"Sim") -> 2 | D18: =COUNTIF(D2:D15,"Sim") -> 0 | E18: =COUNTIF(E2:E15,"Sim") -> 4 | F18: =COUNTIF(F2:F15,"Sim") -> 9 | G18: =COUNTIF(G2:G15,"Sim") -> 9 | H18: =COUNTIF(H2:H15,"Sim") -> 5 | I18: =COUNTIF(I2:I15,"Sim") -> 5 | ... N18: =COUNTIF(N2:N15,"Sim") -> 6
A19: Concorrentes com Parcial | B19: =COUNTIF(B2:B15,"Parcial") -> 1 | C19: =COUNTIF(C2:C15,"Parcial") -> 1 | D19: =COUNTIF(D2:D15,"Parcial") -> 0 | E19: =COUNTIF(E2:E15,"Parcial") -> 0 | F19: =COUNTIF(F2:F15,"Parcial") -> 1 | G19: =COUNTIF(G2:G15,"Parcial") -> 3 | H19: =COUNTIF(H2:H15,"Parcial") -> 0 | I19: =COUNTIF(I2:I15,"Parcial") -> 2 | ... N19: =COUNTIF(N2:N15,"Parcial") -> 3
A20: Sem informação (?) | B20: =COUNTIF(B2:B15,"?") -> 4 | C20: =COUNTIF(C2:C15,"?") -> 4 | D20: =COUNTIF(D2:D15,"?") -> 6 | E20: =COUNTIF(E2:E15,"?") -> 7 | F20: =COUNTIF(F2:F15,"?") -> 3 | G20: =COUNTIF(G2:G15,"?") -> 0 | H20: =COUNTIF(H2:H15,"?") -> 4 | I20: =COUNTIF(I2:I15,"?") -> 5 | ... N20: =COUNTIF(N2:N15,"?") -> 1
A21: % com Sim | B21: =IF(COUNTA(B2:B15)=0,0,B18/COUNTA(B2:B15)) -> 0.071428571 | C21: =IF(COUNTA(C2:C15)=0,0,C18/COUNTA(C2:C15)) -> 0.14285714 | D21: =IF(COUNTA(D2:D15)=0,0,D18/COUNTA(D2:D15)) -> 0 | E21: =IF(COUNTA(E2:E15)=0,0,E18/COUNTA(E2:E15)) -> 0.28571429 | F21: =IF(COUNTA(F2:F15)=0,0,F18/COUNTA(F2:F15)) -> 0.64285714 | G21: =IF(COUNTA(G2:G15)=0,0,G18/COUNTA(G2:G15)) -> 0.64285714 | H21: =IF(COUNTA(H2:H15)=0,0,H18/COUNTA(H2:H15)) -> 0.35714286 | I21: =IF(COUNTA(I2:I15)=0,0,I18/COUNTA(I2:I15)) -> 0.35714286 | ... N21: =IF(COUNTA(N2:N15)=0,0,N18/COUNTA(N2:N15)) -> 0.42857143
A22: Leitura | B22: =IF(B18<=1,"Raro: diferencial",IF(B21>=0.5,"Básico do mercado","Comum")) -> Raro: diferencial | C22: =IF(C18<=1,"Raro: diferencial",IF(C21>=0.5,"Básico do mercado","Comum")) -> Comum | D22: =IF(D18<=1,"Raro: diferencial",IF(D21>=0.5,"Básico do mercado","Comum")) -> Raro: diferencial | E22: =IF(E18<=1,"Raro: diferencial",IF(E21>=0.5,"Básico do mercado","Comum")) -> Comum | F22: =IF(F18<=1,"Raro: diferencial",IF(F21>=0.5,"Básico do mercado","Comum")) -> Básico do mercado | G22: =IF(G18<=1,"Raro: diferencial",IF(G21>=0.5,"Básico do mercado","Comum")) -> Básico do mercado | H22: =IF(H18<=1,"Raro: diferencial",IF(H21>=0.5,"Básico do mercado","Comum")) -> Comum | I22: =IF(I18<=1,"Raro: diferencial",IF(I21>=0.5,"Básico do mercado","Comum")) -> Comum | ... N22: =IF(N18<=1,"Raro: diferencial",IF(N21>=0.5,"Básico do mercado","Comum")) -> Comum
A24: Contagens consideram só as linhas de concorrentes (sem 'Nós'). '?' não conta como Sim: cada '?' é um item a verificar testando o app.

Sheet Premissas
A1: Premissas
A3: Câmbio USD → BRL | B3: 5.4 | C3: Assumido; atualize com a PTAX do dia. Todas as conversões da aba Concorrentes usam esta célula.
